sassy/__init__.py
sassy/example.py
sassy/sassy.abi3.so
sassy_rs-0.1.6.dist-info/METADATA
sassy_rs-0.1.6.dist-info/WHEEL
sassy_rs-0.1.6.dist-info/licenses/LICENSE
sassy_rs-0.1.6.dist-info/RECORD
