Metadata-Version: 2.4
Name: sassy-rs
Version: 0.1.6
Classifier: Programming Language :: Rust
License-File: LICENSE
Summary: Fast approximate string searching using SIMD
Author-email: Rick beeloo <biobeeloo@gmail.com>, Ragnar Groot Koerkamp <ragnar.grootkoerkamp@gmail.com >
License-Expression: MIT
Requires-Python: >=3.8
Project-URL: Homepage, https://github.com/RagnarGrootKoerkamp/sassy
Project-URL: Repository, https://github.com/RagnarGrootKoerkamp/sassy
Project-URL: Documentation, https://github.com/RagnarGrootKoerkamp/sassy/blob/master/python/README.md
